server/__init__.py
server/server_gui.py
server/server_side.py
server/common/__init__.py
server/common/decorators.py
server/common/descryptors.py
server/common/errors.py
server/common/metaclasses.py
server/common/utils.py
server/common/variables.py
server/logs/__init__.py
server/logs/client_log_config.py
server/logs/log_config.py
server/logs/server_log_config.py
server/server/__init__.py
server/server/add_user.py
server/server/config_window.py
server/server/core.py
server/server/database.py
server/server/main_window.py
server/server/remove_user.py
server/server/stat_window.py
server/unit_tests/__init__.py
server/unit_tests/test_client.py
server/unit_tests/test_server.py
server/unit_tests/test_utils.py
xartiou_csa_server-0.0.1.data/scripts/server_run
xartiou_csa_server-0.0.1.dist-info/METADATA
xartiou_csa_server-0.0.1.dist-info/WHEEL
xartiou_csa_server-0.0.1.dist-info/top_level.txt
xartiou_csa_server-0.0.1.dist-info/RECORD
