Metadata-Version: 2.1
Name: xartiou-csa-server
Version: 0.0.1
Summary: Client Server APP server_side
Home-page: UNKNOWN
Author: Ivan Xartiou
Author-email: xartiou@gmail.com
License: UNKNOWN
Platform: UNKNOWN
Requires-Dist: PyQt5
Requires-Dist: sqlalchemy
Requires-Dist: pycryptodome
Requires-Dist: pycryptodomex
